demin/__init__.py
demin/main.py
demin-0.0.2.dist-info/METADATA
demin-0.0.2.dist-info/WHEEL
demin-0.0.2.dist-info/licenses/LICENSE
demin-0.0.2.dist-info/RECORD
