Metadata-Version: 2.1
Name: demin
Version: 0.0.2
Summary: Useful Data Science functions for Geometallurgical Analysis.
Project-URL: Homepage, https://github.com/gstvortiz/demin
Project-URL: Issues, https://github.com/gstvortiz/demin/issues
Author-email: Gustavo Ortiz <gstvortiz@hotmail.com>
License-File: LICENSE
Classifier: License :: OSI Approved :: MIT License
Classifier: Operating System :: OS Independent
Classifier: Programming Language :: Python :: 3
Requires-Python: >=3.10.12
